{
    "version": "0.2.1",
    "architecture": {
        "32bit": {
            "url": "https://github.com/opsani/cli/releases/download/v0.2.1/opsani-cli_0.2.1_windows_386.zip",
            "bin": [
                "bin/opsani.exe"
            ],
            "hash": "e63b283f3591388689399e9326f126c1fcf39b3b275d71230d68aead8bfe075b"
        },
        "64bit": {
            "url": "https://github.com/opsani/cli/releases/download/v0.2.1/opsani-cli_0.2.1_windows_amd64.zip",
            "bin": [
                "bin/opsani.exe"
            ],
            "hash": "8ae92ba59e81734a0d386216ebc1d004142812625e24e699dddf0ad99e65bacd"
        }
    },
    "homepage": "https://github.com/opsani/cli",
    "license": "Apache 2.0",
    "description": "Opsani CLI"
}